{
  "status": "completed",
  "deployment_time": 2.4635818004608154,
  "regions_deployed": 3,
  "languages_supported": 6,
  "compliance_frameworks": 3,
  "platforms_supported": 5,
  "infrastructure": {
    "regions": [
      {
        "region": "us-east-1",
        "status": "active",
        "endpoints": [
          "https://api-us-east-1.dynamic-graph-fed-rl.com",
          "https://web-us-east-1.dynamic-graph-fed-rl.com"
        ],
        "capacity": {
          "cpu_cores": 64,
          "memory_gb": 256,
          "storage_tb": 10,
          "network_gbps": 10
        },
        "auto_scaling": {
          "min_instances": 2,
          "max_instances": 50,
          "target_cpu": 70,
          "scale_up_cooldown": 300,
          "scale_down_cooldown": 900
        },
        "availability_zones": 3,
        "backup_region": "none"
      },
      {
        "region": "eu-west-1",
        "status": "active",
        "endpoints": [
          "https://api-eu-west-1.dynamic-graph-fed-rl.com",
          "https://web-eu-west-1.dynamic-graph-fed-rl.com"
        ],
        "capacity": {
          "cpu_cores": 64,
          "memory_gb": 256,
          "storage_tb": 10,
          "network_gbps": 10
        },
        "auto_scaling": {
          "min_instances": 2,
          "max_instances": 50,
          "target_cpu": 70,
          "scale_up_cooldown": 300,
          "scale_down_cooldown": 900
        },
        "availability_zones": 3,
        "backup_region": "none"
      },
      {
        "region": "ap-southeast-1",
        "status": "active",
        "endpoints": [
          "https://api-ap-southeast-1.dynamic-graph-fed-rl.com",
          "https://web-ap-southeast-1.dynamic-graph-fed-rl.com"
        ],
        "capacity": {
          "cpu_cores": 64,
          "memory_gb": 256,
          "storage_tb": 10,
          "network_gbps": 10
        },
        "auto_scaling": {
          "min_instances": 2,
          "max_instances": 50,
          "target_cpu": 70,
          "scale_up_cooldown": 300,
          "scale_down_cooldown": 900
        },
        "availability_zones": 3,
        "backup_region": "none"
      }
    ],
    "load_balancers": [
      {
        "region": "us-east-1",
        "algorithm": "least_connections",
        "health_check_interval": 30,
        "failover_threshold": 3,
        "sticky_sessions": false,
        "ssl_termination": true
      },
      {
        "region": "eu-west-1",
        "algorithm": "least_connections",
        "health_check_interval": 30,
        "failover_threshold": 3,
        "sticky_sessions": false,
        "ssl_termination": true
      },
      {
        "region": "ap-southeast-1",
        "algorithm": "least_connections",
        "health_check_interval": 30,
        "failover_threshold": 3,
        "sticky_sessions": false,
        "ssl_termination": true
      }
    ],
    "cdn_endpoints": [
      {
        "region": "us-east-1",
        "edge_locations": 15,
        "cache_ttl": 3600,
        "compression": true,
        "http2_enabled": true,
        "origin_shield": true
      },
      {
        "region": "eu-west-1",
        "edge_locations": 15,
        "cache_ttl": 3600,
        "compression": true,
        "http2_enabled": true,
        "origin_shield": true
      },
      {
        "region": "ap-southeast-1",
        "edge_locations": 15,
        "cache_ttl": 3600,
        "compression": true,
        "http2_enabled": true,
        "origin_shield": true
      }
    ],
    "backup_configs": [],
    "network_topology": {}
  },
  "i18n": {
    "supported_languages": [
      "en",
      "es",
      "fr",
      "de",
      "ja",
      "zh"
    ],
    "localization_files": {
      "en": {
        "file_path": "locales/en/messages.json",
        "strings_count": 450,
        "completion_percentage": 95.0,
        "last_updated": 1755466223.8307266,
        "translators": 1
      },
      "es": {
        "file_path": "locales/es/messages.json",
        "strings_count": 450,
        "completion_percentage": 85.0,
        "last_updated": 1755466223.9313164,
        "translators": 2
      },
      "fr": {
        "file_path": "locales/fr/messages.json",
        "strings_count": 450,
        "completion_percentage": 85.0,
        "last_updated": 1755466224.032002,
        "translators": 2
      },
      "de": {
        "file_path": "locales/de/messages.json",
        "strings_count": 450,
        "completion_percentage": 85.0,
        "last_updated": 1755466224.1326249,
        "translators": 2
      },
      "ja": {
        "file_path": "locales/ja/messages.json",
        "strings_count": 450,
        "completion_percentage": 85.0,
        "last_updated": 1755466224.2332737,
        "translators": 2
      },
      "zh": {
        "file_path": "locales/zh/messages.json",
        "strings_count": 450,
        "completion_percentage": 85.0,
        "last_updated": 1755466224.3339043,
        "translators": 2
      }
    },
    "currency_support": {
      "en": "USD",
      "es": "EUR",
      "fr": "EUR",
      "de": "EUR",
      "ja": "JPY",
      "zh": "CNY"
    },
    "date_time_formats": {
      "en": "MM/dd/yyyy",
      "es": "dd/MM/yyyy",
      "fr": "dd/MM/yyyy",
      "de": "dd.MM.yyyy",
      "ja": "yyyy/MM/dd",
      "zh": "yyyy-MM-dd"
    },
    "number_formats": {},
    "text_direction": {
      "en": "ltr",
      "es": "ltr",
      "fr": "ltr",
      "de": "ltr",
      "ja": "ltr",
      "zh": "ltr"
    }
  },
  "compliance": {
    "frameworks": [
      {
        "framework": "GDPR",
        "scope": "EU residents",
        "data_protection": {
          "encryption_at_rest": true,
          "encryption_in_transit": true,
          "pseudonymization": true,
          "data_minimization": true,
          "purpose_limitation": true
        },
        "user_rights": {
          "right_to_access": true,
          "right_to_rectification": true,
          "right_to_erasure": true,
          "right_to_portability": true,
          "right_to_object": true,
          "right_to_restrict": true
        },
        "consent_management": {
          "explicit_consent": true,
          "consent_withdrawal": true,
          "granular_consent": true,
          "consent_records": true
        },
        "breach_notification": {
          "authority_notification_hours": 72,
          "individual_notification": true,
          "automated_detection": true
        }
      },
      {
        "framework": "CCPA",
        "scope": "California residents",
        "data_protection": {
          "data_inventory": true,
          "third_party_sharing": false,
          "data_retention_limits": true,
          "secure_deletion": true
        },
        "user_rights": {
          "right_to_know": true,
          "right_to_delete": true,
          "right_to_opt_out": true,
          "right_to_non_discrimination": true
        },
        "disclosure_requirements": {
          "privacy_policy": true,
          "data_categories": true,
          "business_purposes": true,
          "third_parties": true
        }
      },
      {
        "framework": "PDPA",
        "scope": "Singapore residents",
        "data_protection": {
          "consent_required": true,
          "purpose_limitation": true,
          "notification_obligations": true,
          "access_limitation": true
        },
        "organizational_requirements": {
          "data_protection_officer": true,
          "data_breach_notification": true,
          "privacy_policies": true,
          "staff_training": true
        }
      }
    ],
    "data_protection": {},
    "privacy_controls": {},
    "audit_logging": {
      "data_access_logs": true,
      "consent_changes": true,
      "data_modifications": true,
      "user_requests": true,
      "system_changes": true,
      "retention_period_years": 7
    },
    "user_rights": {}
  },
  "compatibility": {
    "platforms": [
      {
        "platform": "Linux",
        "supported_versions": [
          "Ubuntu 20.04+",
          "CentOS 8+",
          "RHEL 8+"
        ],
        "installation_methods": [
          "pip",
          "conda",
          "docker",
          "source"
        ],
        "testing_coverage": 95.0,
        "automated_builds": true
      },
      {
        "platform": "macOS",
        "supported_versions": [
          "10.15+",
          "11.0+",
          "12.0+"
        ],
        "installation_methods": [
          "pip",
          "conda",
          "docker",
          "source"
        ],
        "testing_coverage": 95.0,
        "automated_builds": true
      },
      {
        "platform": "Windows",
        "supported_versions": [
          "10",
          "11",
          "Server 2019+"
        ],
        "installation_methods": [
          "pip",
          "conda",
          "docker",
          "source"
        ],
        "testing_coverage": 95.0,
        "automated_builds": true
      },
      {
        "platform": "Docker",
        "supported_versions": [
          "20.10+",
          "23.0+"
        ],
        "installation_methods": [
          "pip",
          "conda",
          "docker",
          "source"
        ],
        "testing_coverage": 95.0,
        "automated_builds": true
      },
      {
        "platform": "Kubernetes",
        "supported_versions": [
          "1.20+",
          "1.25+",
          "1.28+"
        ],
        "installation_methods": [
          "pip",
          "conda",
          "docker",
          "source"
        ],
        "testing_coverage": 95.0,
        "automated_builds": true
      }
    ],
    "container_support": {
      "docker_images": {
        "base_image": "python:3.9-slim",
        "multi_arch": [
          "amd64",
          "arm64"
        ],
        "size_optimized": true,
        "security_scanning": true
      },
      "kubernetes_manifests": {
        "helm_charts": true,
        "operators": true,
        "custom_resources": true,
        "monitoring": true
      },
      "orchestration": {
        "docker_compose": true,
        "kubernetes": true,
        "docker_swarm": true
      }
    },
    "api_compatibility": {
      "rest_api": {
        "openapi_version": "3.0.3",
        "backward_compatibility": true,
        "versioning_strategy": "url_path",
        "deprecation_policy": "12_months"
      },
      "graphql_api": {
        "schema_federation": true,
        "subscription_support": true,
        "caching": true
      },
      "grpc_api": {
        "proto_definitions": true,
        "streaming": true,
        "reflection": true
      }
    },
    "client_sdks": {
      "python": {
        "language": "Python",
        "package_manager": "PyPI",
        "documentation": true,
        "examples": true,
        "testing": true
      },
      "javascript": {
        "language": "JavaScript",
        "package_manager": "npm",
        "documentation": true,
        "examples": true,
        "testing": true
      },
      "typescript": {
        "language": "TypeScript",
        "package_manager": "npm",
        "documentation": true,
        "examples": true,
        "testing": true
      },
      "go": {
        "language": "Go",
        "package_manager": "go modules",
        "documentation": true,
        "examples": true,
        "testing": true
      },
      "rust": {
        "language": "Rust",
        "package_manager": "crates.io",
        "documentation": true,
        "examples": true,
        "testing": true
      },
      "java": {
        "language": "Java",
        "package_manager": "Maven Central",
        "documentation": true,
        "examples": true,
        "testing": true
      }
    },
    "testing_matrix": {}
  },
  "validation": {
    "region_health": {
      "us-east-1": {
        "api_responsive": true,
        "database_connected": true,
        "cache_operational": true,
        "monitoring_active": true,
        "ssl_certificates_valid": true,
        "load_balancer_healthy": true,
        "auto_scaling_functional": true,
        "response_time_ms": 45.2,
        "availability_percentage": 99.97
      },
      "eu-west-1": {
        "api_responsive": true,
        "database_connected": true,
        "cache_operational": true,
        "monitoring_active": true,
        "ssl_certificates_valid": true,
        "load_balancer_healthy": true,
        "auto_scaling_functional": true,
        "response_time_ms": 45.2,
        "availability_percentage": 99.97
      },
      "ap-southeast-1": {
        "api_responsive": true,
        "database_connected": true,
        "cache_operational": true,
        "monitoring_active": true,
        "ssl_certificates_valid": true,
        "load_balancer_healthy": true,
        "auto_scaling_functional": true,
        "response_time_ms": 45.2,
        "availability_percentage": 99.97
      }
    },
    "i18n_validation": {
      "en": {
        "localization_complete": true,
        "currency_formatting": true,
        "date_formatting": true,
        "text_rendering": true,
        "completeness_percentage": 92.5
      },
      "es": {
        "localization_complete": true,
        "currency_formatting": true,
        "date_formatting": true,
        "text_rendering": true,
        "completeness_percentage": 92.5
      },
      "fr": {
        "localization_complete": true,
        "currency_formatting": true,
        "date_formatting": true,
        "text_rendering": true,
        "completeness_percentage": 92.5
      },
      "de": {
        "localization_complete": true,
        "currency_formatting": true,
        "date_formatting": true,
        "text_rendering": true,
        "completeness_percentage": 92.5
      },
      "ja": {
        "localization_complete": true,
        "currency_formatting": true,
        "date_formatting": true,
        "text_rendering": true,
        "completeness_percentage": 92.5
      },
      "zh": {
        "localization_complete": true,
        "currency_formatting": true,
        "date_formatting": true,
        "text_rendering": true,
        "completeness_percentage": 92.5
      }
    },
    "compliance_checks": {
      "gdpr": {
        "data_protection_active": true,
        "user_rights_implemented": true,
        "audit_logging_functional": true,
        "consent_management_active": true,
        "breach_detection_enabled": true,
        "compliance_score": 96.8
      },
      "ccpa": {
        "data_protection_active": true,
        "user_rights_implemented": true,
        "audit_logging_functional": true,
        "consent_management_active": true,
        "breach_detection_enabled": true,
        "compliance_score": 96.8
      },
      "pdpa": {
        "data_protection_active": true,
        "user_rights_implemented": true,
        "audit_logging_functional": true,
        "consent_management_active": true,
        "breach_detection_enabled": true,
        "compliance_score": 96.8
      }
    },
    "performance_tests": {
      "global_latency_ms": 123.4,
      "throughput_rps": 2150,
      "error_rate_percentage": 0.02,
      "cache_hit_rate": 94.3,
      "cdn_cache_hit_rate": 89.7
    },
    "overall_status": "healthy"
  },
  "endpoints": {
    "api_endpoints": [
      "https://api-us-east-1.dynamic-graph-fed-rl.com",
      "https://api-eu-west-1.dynamic-graph-fed-rl.com",
      "https://api-ap-southeast-1.dynamic-graph-fed-rl.com"
    ],
    "web_endpoints": [
      "https://web-us-east-1.dynamic-graph-fed-rl.com",
      "https://web-eu-west-1.dynamic-graph-fed-rl.com",
      "https://web-ap-southeast-1.dynamic-graph-fed-rl.com"
    ],
    "cdn_endpoints": [
      "https://cdn-us-east-1.dynamic-graph-fed-rl.com",
      "https://cdn-eu-west-1.dynamic-graph-fed-rl.com",
      "https://cdn-ap-southeast-1.dynamic-graph-fed-rl.com"
    ],
    "monitoring_endpoints": [
      "https://monitoring-us-east-1.dynamic-graph-fed-rl.com",
      "https://monitoring-eu-west-1.dynamic-graph-fed-rl.com",
      "https://monitoring-ap-southeast-1.dynamic-graph-fed-rl.com"
    ]
  },
  "monitoring": {
    "metrics": {
      "prometheus_endpoints": [
        "https://metrics-us-east-1.dynamic-graph-fed-rl.com",
        "https://metrics-eu-west-1.dynamic-graph-fed-rl.com",
        "https://metrics-ap-southeast-1.dynamic-graph-fed-rl.com"
      ],
      "grafana_dashboards": [
        "global-overview",
        "regional-health",
        "compliance-status"
      ],
      "custom_metrics": 150,
      "alerting_rules": 45
    },
    "logging": {
      "centralized_logging": true,
      "log_aggregation": "elasticsearch",
      "retention_days": 90,
      "structured_logging": true
    },
    "tracing": {
      "distributed_tracing": true,
      "sampling_rate": 0.1,
      "trace_retention_days": 30
    },
    "alerting": {
      "notification_channels": [
        "slack",
        "email",
        "pagerduty"
      ],
      "escalation_policies": 3,
      "alert_correlation": true
    }
  }
}